onyx_database/__init__.py
onyx_database/ai.py
onyx_database/config.py
onyx_database/errors.py
onyx_database/http.py
onyx_database/onyx.py
onyx_database/onyx_async.py
onyx_database/query_builder.py
onyx_database/query_builder_async.py
onyx_database/query_results.py
onyx_database/query_results_async.py
onyx_database/stream.py
onyx_database/types.py
onyx_database/helpers/__init__.py
onyx_database/helpers/aggregates.py
onyx_database/helpers/conditions.py
onyx_database/helpers/sort.py
onyx_database-2.0.0.dist-info/METADATA
onyx_database-2.0.0.dist-info/WHEEL
onyx_database-2.0.0.dist-info/licenses/LICENSE
onyx_database-2.0.0.dist-info/RECORD
