Metadata-Version: 2.4
Name: onyx-database
Version: 2.0.0
Summary: Python client SDK for Onyx Cloud Database (builder-pattern API and schema helpers)
Project-URL: Homepage, https://onyx.dev
Project-URL: Repository, https://github.com/OnyxDevTools/onyx-database-python
Project-URL: Documentation, https://onyx.dev/documentation/
Author: Onyx Dev Tools
License: MIT
License-File: LICENSE
Keywords: database,onyx,query,sdk
Classifier: Intended Audience :: Developers
Classifier: License :: OSI Approved :: MIT License
Classifier: Programming Language :: Python :: 3
Classifier: Programming Language :: Python :: 3 :: Only
Classifier: Programming Language :: Python :: 3.11
Classifier: Programming Language :: Python :: 3.12
Classifier: Programming Language :: Python :: 3.13
Classifier: Topic :: Database
Classifier: Topic :: Software Development :: Libraries
Requires-Python: >=3.11
